README.md
setup.cfg
setup.py
simplewiktionary/__init__.py
simplewiktionary/code.py
simplewiktionary/tests.py
simplewiktionary.egg-info/PKG-INFO
simplewiktionary.egg-info/SOURCES.txt
simplewiktionary.egg-info/dependency_links.txt
simplewiktionary.egg-info/not-zip-safe
simplewiktionary.egg-info/requires.txt
simplewiktionary.egg-info/top_level.txt