Metadata-Version: 1.0
Name: simplewiktionary
Version: 0.1
Summary: Provides access to simple definitions of English words from  Wiktionary
Home-page: https://github.com/57uff3r/simple-wiktionary
Author: Andrey Korchak
Author-email: 57uff3r@gmail.com
License: MIT
Platform: UNKNOWN
